LICENSE
MANIFEST.in
README.md
pyproject.toml
setup.cfg
setup.py
django_adsense_injector/__init__.py
django_adsense_injector/admin.py
django_adsense_injector/apps.py
django_adsense_injector/models.py
django_adsense_injector/tests.py
django_adsense_injector/views.py
django_adsense_injector.egg-info/PKG-INFO
django_adsense_injector.egg-info/SOURCES.txt
django_adsense_injector.egg-info/dependency_links.txt
django_adsense_injector.egg-info/requires.txt
django_adsense_injector.egg-info/top_level.txt
django_adsense_injector/migrations/__init__.py
django_adsense_injector/templatetags/__init__.py
django_adsense_injector/templatetags/adsense_tags.py